{"number":79,"name":"سُورَةُ النَّازِعَاتِ","numberOfAyahs":46,"ayahs":[{"numberInQuran":5713,"numberInSurah":1,"audio":"https://cdn.islamic.network/quran/audio/128/ar.alafasy/5713.mp3","text":"بِسْمِ ٱللَّهِ ٱلرَّحْمَٰنِ ٱلرَّحِيمِ وَٱلنَّٰزِعَٰتِ غَرْقًۭا","juz":30,"page":583,"sajda":false},{"numberInQuran":5714,"numberInSurah":2,"audio":"https://cdn.islamic.network/quran/audio/128/ar.alafasy/5714.mp3","text":"وَٱلنَّٰشِطَٰتِ نَشْطًۭا","juz":30,"page":583,"sajda":false},{"numberInQuran":5715,"numberInSurah":3,"audio":"https://cdn.islamic.network/quran/audio/128/ar.alafasy/5715.mp3","text":"وَٱلسَّٰبِحَٰتِ سَبْحًۭا","juz":30,"page":583,"sajda":false},{"numberInQuran":5716,"numberInSurah":4,"audio":"https://cdn.islamic.network/quran/audio/128/ar.alafasy/5716.mp3","text":"فَٱلسَّٰبِقَٰتِ سَبْقًۭا","juz":30,"page":583,"sajda":false},{"numberInQuran":5717,"numberInSurah":5,"audio":"https://cdn.islamic.network/quran/audio/128/ar.alafasy/5717.mp3","text":"فَٱلْمُدَبِّرَٰتِ أَمْرًۭا","juz":30,"page":583,"sajda":false},{"numberInQuran":5718,"numberInSurah":6,"audio":"https://cdn.islamic.network/quran/audio/128/ar.alafasy/5718.mp3","text":"يَوْمَ تَرْجُفُ ٱلرَّاجِفَةُ","juz":30,"page":583,"sajda":false},{"numberInQuran":5719,"numberInSurah":7,"audio":"https://cdn.islamic.network/quran/audio/128/ar.alafasy/5719.mp3","text":"تَتْبَعُهَا ٱلرَّادِفَةُ","juz":30,"page":583,"sajda":false},{"numberInQuran":5720,"numberInSurah":8,"audio":"https://cdn.islamic.network/quran/audio/128/ar.alafasy/5720.mp3","text":"قُلُوبٌۭ يَوْمَئِذٍۢ وَاجِفَةٌ","juz":30,"page":583,"sajda":false},{"numberInQuran":5721,"numberInSurah":9,"audio":"https://cdn.islamic.network/quran/audio/128/ar.alafasy/5721.mp3","text":"أَبْصَٰرُهَا خَٰشِعَةٌۭ","juz":30,"page":583,"sajda":false},{"numberInQuran":5722,"numberInSurah":10,"audio":"https://cdn.islamic.network/quran/audio/128/ar.alafasy/5722.mp3","text":"يَقُولُونَ أَءِنَّا لَمَرْدُودُونَ فِى ٱلْحَافِرَةِ","juz":30,"page":583,"sajda":false},{"numberInQuran":5723,"numberInSurah":11,"audio":"https://cdn.islamic.network/quran/audio/128/ar.alafasy/5723.mp3","text":"أَءِذَا كُنَّا عِظَٰمًۭا نَّخِرَةًۭ","juz":30,"page":583,"sajda":false},{"numberInQuran":5724,"numberInSurah":12,"audio":"https://cdn.islamic.network/quran/audio/128/ar.alafasy/5724.mp3","text":"قَالُوا۟ تِلْكَ إِذًۭا كَرَّةٌ خَاسِرَةٌۭ","juz":30,"page":583,"sajda":false},{"numberInQuran":5725,"numberInSurah":13,"audio":"https://cdn.islamic.network/quran/audio/128/ar.alafasy/5725.mp3","text":"فَإِنَّمَا هِىَ زَجْرَةٌۭ وَٰحِدَةٌۭ","juz":30,"page":583,"sajda":false},{"numberInQuran":5726,"numberInSurah":14,"audio":"https://cdn.islamic.network/quran/audio/128/ar.alafasy/5726.mp3","text":"فَإِذَا هُم بِٱلسَّاهِرَةِ","juz":30,"page":583,"sajda":false},{"numberInQuran":5727,"numberInSurah":15,"audio":"https://cdn.islamic.network/quran/audio/128/ar.alafasy/5727.mp3","text":"هَلْ أَتَىٰكَ حَدِيثُ مُوسَىٰٓ","juz":30,"page":583,"sajda":false},{"numberInQuran":5728,"numberInSurah":16,"audio":"https://cdn.islamic.network/quran/audio/128/ar.alafasy/5728.mp3","text":"إِذْ نَادَىٰهُ رَبُّهُۥ بِٱلْوَادِ ٱلْمُقَدَّسِ طُوًى","juz":30,"page":584,"sajda":false},{"numberInQuran":5729,"numberInSurah":17,"audio":"https://cdn.islamic.network/quran/audio/128/ar.alafasy/5729.mp3","text":"ٱذْهَبْ إِلَىٰ فِرْعَوْنَ إِنَّهُۥ طَغَىٰ","juz":30,"page":584,"sajda":false},{"numberInQuran":5730,"numberInSurah":18,"audio":"https://cdn.islamic.network/quran/audio/128/ar.alafasy/5730.mp3","text":"فَقُلْ هَل لَّكَ إِلَىٰٓ أَن تَزَكَّىٰ","juz":30,"page":584,"sajda":false},{"numberInQuran":5731,"numberInSurah":19,"audio":"https://cdn.islamic.network/quran/audio/128/ar.alafasy/5731.mp3","text":"وَأَهْدِيَكَ إِلَىٰ رَبِّكَ فَتَخْشَىٰ","juz":30,"page":584,"sajda":false},{"numberInQuran":5732,"numberInSurah":20,"audio":"https://cdn.islamic.network/quran/audio/128/ar.alafasy/5732.mp3","text":"فَأَرَىٰهُ ٱلْءَايَةَ ٱلْكُبْرَىٰ","juz":30,"page":584,"sajda":false},{"numberInQuran":5733,"numberInSurah":21,"audio":"https://cdn.islamic.network/quran/audio/128/ar.alafasy/5733.mp3","text":"فَكَذَّبَ وَعَصَىٰ","juz":30,"page":584,"sajda":false},{"numberInQuran":5734,"numberInSurah":22,"audio":"https://cdn.islamic.network/quran/audio/128/ar.alafasy/5734.mp3","text":"ثُمَّ أَدْبَرَ يَسْعَىٰ","juz":30,"page":584,"sajda":false},{"numberInQuran":5735,"numberInSurah":23,"audio":"https://cdn.islamic.network/quran/audio/128/ar.alafasy/5735.mp3","text":"فَحَشَرَ فَنَادَىٰ","juz":30,"page":584,"sajda":false},{"numberInQuran":5736,"numberInSurah":24,"audio":"https://cdn.islamic.network/quran/audio/128/ar.alafasy/5736.mp3","text":"فَقَالَ أَنَا۠ رَبُّكُمُ ٱلْأَعْلَىٰ","juz":30,"page":584,"sajda":false},{"numberInQuran":5737,"numberInSurah":25,"audio":"https://cdn.islamic.network/quran/audio/128/ar.alafasy/5737.mp3","text":"فَأَخَذَهُ ٱللَّهُ نَكَالَ ٱلْءَاخِرَةِ وَٱلْأُولَىٰٓ","juz":30,"page":584,"sajda":false},{"numberInQuran":5738,"numberInSurah":26,"audio":"https://cdn.islamic.network/quran/audio/128/ar.alafasy/5738.mp3","text":"إِنَّ فِى ذَٰلِكَ لَعِبْرَةًۭ لِّمَن يَخْشَىٰٓ","juz":30,"page":584,"sajda":false},{"numberInQuran":5739,"numberInSurah":27,"audio":"https://cdn.islamic.network/quran/audio/128/ar.alafasy/5739.mp3","text":"ءَأَنتُمْ أَشَدُّ خَلْقًا أَمِ ٱلسَّمَآءُ ۚ بَنَىٰهَا","juz":30,"page":584,"sajda":false},{"numberInQuran":5740,"numberInSurah":28,"audio":"https://cdn.islamic.network/quran/audio/128/ar.alafasy/5740.mp3","text":"رَفَعَ سَمْكَهَا فَسَوَّىٰهَا","juz":30,"page":584,"sajda":false},{"numberInQuran":5741,"numberInSurah":29,"audio":"https://cdn.islamic.network/quran/audio/128/ar.alafasy/5741.mp3","text":"وَأَغْطَشَ لَيْلَهَا وَأَخْرَجَ ضُحَىٰهَا","juz":30,"page":584,"sajda":false},{"numberInQuran":5742,"numberInSurah":30,"audio":"https://cdn.islamic.network/quran/audio/128/ar.alafasy/5742.mp3","text":"وَٱلْأَرْضَ بَعْدَ ذَٰلِكَ دَحَىٰهَآ","juz":30,"page":584,"sajda":false},{"numberInQuran":5743,"numberInSurah":31,"audio":"https://cdn.islamic.network/quran/audio/128/ar.alafasy/5743.mp3","text":"أَخْرَجَ مِنْهَا مَآءَهَا وَمَرْعَىٰهَا","juz":30,"page":584,"sajda":false},{"numberInQuran":5744,"numberInSurah":32,"audio":"https://cdn.islamic.network/quran/audio/128/ar.alafasy/5744.mp3","text":"وَٱلْجِبَالَ أَرْسَىٰهَا","juz":30,"page":584,"sajda":false},{"numberInQuran":5745,"numberInSurah":33,"audio":"https://cdn.islamic.network/quran/audio/128/ar.alafasy/5745.mp3","text":"مَتَٰعًۭا لَّكُمْ وَلِأَنْعَٰمِكُمْ","juz":30,"page":584,"sajda":false},{"numberInQuran":5746,"numberInSurah":34,"audio":"https://cdn.islamic.network/quran/audio/128/ar.alafasy/5746.mp3","text":"فَإِذَا جَآءَتِ ٱلطَّآمَّةُ ٱلْكُبْرَىٰ","juz":30,"page":584,"sajda":false},{"numberInQuran":5747,"numberInSurah":35,"audio":"https://cdn.islamic.network/quran/audio/128/ar.alafasy/5747.mp3","text":"يَوْمَ يَتَذَكَّرُ ٱلْإِنسَٰنُ مَا سَعَىٰ","juz":30,"page":584,"sajda":false},{"numberInQuran":5748,"numberInSurah":36,"audio":"https://cdn.islamic.network/quran/audio/128/ar.alafasy/5748.mp3","text":"وَبُرِّزَتِ ٱلْجَحِيمُ لِمَن يَرَىٰ","juz":30,"page":584,"sajda":false},{"numberInQuran":5749,"numberInSurah":37,"audio":"https://cdn.islamic.network/quran/audio/128/ar.alafasy/5749.mp3","text":"فَأَمَّا مَن طَغَىٰ","juz":30,"page":584,"sajda":false},{"numberInQuran":5750,"numberInSurah":38,"audio":"https://cdn.islamic.network/quran/audio/128/ar.alafasy/5750.mp3","text":"وَءَاثَرَ ٱلْحَيَوٰةَ ٱلدُّنْيَا","juz":30,"page":584,"sajda":false},{"numberInQuran":5751,"numberInSurah":39,"audio":"https://cdn.islamic.network/quran/audio/128/ar.alafasy/5751.mp3","text":"فَإِنَّ ٱلْجَحِيمَ هِىَ ٱلْمَأْوَىٰ","juz":30,"page":584,"sajda":false},{"numberInQuran":5752,"numberInSurah":40,"audio":"https://cdn.islamic.network/quran/audio/128/ar.alafasy/5752.mp3","text":"وَأَمَّا مَنْ خَافَ مَقَامَ رَبِّهِۦ وَنَهَى ٱلنَّفْسَ عَنِ ٱلْهَوَىٰ","juz":30,"page":584,"sajda":false},{"numberInQuran":5753,"numberInSurah":41,"audio":"https://cdn.islamic.network/quran/audio/128/ar.alafasy/5753.mp3","text":"فَإِنَّ ٱلْجَنَّةَ هِىَ ٱلْمَأْوَىٰ","juz":30,"page":584,"sajda":false},{"numberInQuran":5754,"numberInSurah":42,"audio":"https://cdn.islamic.network/quran/audio/128/ar.alafasy/5754.mp3","text":"يَسْـَٔلُونَكَ عَنِ ٱلسَّاعَةِ أَيَّانَ مُرْسَىٰهَا","juz":30,"page":584,"sajda":false},{"numberInQuran":5755,"numberInSurah":43,"audio":"https://cdn.islamic.network/quran/audio/128/ar.alafasy/5755.mp3","text":"فِيمَ أَنتَ مِن ذِكْرَىٰهَآ","juz":30,"page":584,"sajda":false},{"numberInQuran":5756,"numberInSurah":44,"audio":"https://cdn.islamic.network/quran/audio/128/ar.alafasy/5756.mp3","text":"إِلَىٰ رَبِّكَ مُنتَهَىٰهَآ","juz":30,"page":584,"sajda":false},{"numberInQuran":5757,"numberInSurah":45,"audio":"https://cdn.islamic.network/quran/audio/128/ar.alafasy/5757.mp3","text":"إِنَّمَآ أَنتَ مُنذِرُ مَن يَخْشَىٰهَا","juz":30,"page":584,"sajda":false},{"numberInQuran":5758,"numberInSurah":46,"audio":"https://cdn.islamic.network/quran/audio/128/ar.alafasy/5758.mp3","text":"كَأَنَّهُمْ يَوْمَ يَرَوْنَهَا لَمْ يَلْبَثُوٓا۟ إِلَّا عَشِيَّةً أَوْ ضُحَىٰهَا","juz":30,"page":584,"sajda":false}]}